k3wsjobd/__init__.py
k3wsjobd/synopsis.py
k3wsjobd/wsjobd.py
k3wsjobd-0.1.4.dist-info/licenses/LICENSE
k3wsjobd-0.1.4.dist-info/METADATA
k3wsjobd-0.1.4.dist-info/WHEEL
k3wsjobd-0.1.4.dist-info/top_level.txt
k3wsjobd-0.1.4.dist-info/RECORD
