Metadata-Version: 2.4
Name: k3wsjobd
Version: 0.1.4
Summary: Gevent-based WebSocket server for async job processing
Author-email: Zhang Yanpo <drdr.xp@gmail.com>
License: MIT
Project-URL: Homepage, https://github.com/pykit3/k3wsjobd
Project-URL: Documentation, https://k3wsjobd.readthedocs.io
Keywords: websocket,gevent,job,async,server
Classifier: Development Status :: 4 - Beta
Classifier: Intended Audience :: Developers
Classifier: Topic :: Software Development :: Libraries
Classifier: License :: OSI Approved :: MIT License
Classifier: Programming Language :: Python :: 3
Classifier: Programming Language :: Python :: 3.9
Classifier: Programming Language :: Python :: 3.10
Classifier: Programming Language :: Python :: 3.11
Classifier: Programming Language :: Python :: 3.12
Requires-Python: >=3.9
License-File: LICENSE
Requires-Dist: gevent-websocket
Requires-Dist: psutil
Requires-Dist: k3thread
Requires-Dist: k3utfjson
Requires-Dist: k3jobq
Provides-Extra: dev
Requires-Dist: pytest>=7.0; extra == "dev"
Requires-Dist: ruff; extra == "dev"
Requires-Dist: coverage; extra == "dev"
Requires-Dist: k3ut; extra == "dev"
Requires-Dist: k3proc; extra == "dev"
Requires-Dist: k3daemonize; extra == "dev"
Requires-Dist: websocket-client; extra == "dev"
Provides-Extra: publish
Requires-Dist: build; extra == "publish"
Requires-Dist: twine; extra == "publish"
Requires-Dist: pk3; extra == "publish"
Provides-Extra: docs
Requires-Dist: mkdocs>=1.5; extra == "docs"
Requires-Dist: mkdocs-material>=9.0; extra == "docs"
Requires-Dist: mkdocstrings[python]>=0.24; extra == "docs"
Dynamic: license-file
